cdkactions/__init__.py
cdkactions/py.typed
cdkactions/_jsii/__init__.py
cdkactions/_jsii/cdkactions@0.2.3.jsii.tgz
cdkactions-0.2.3.dist-info/METADATA
cdkactions-0.2.3.dist-info/WHEEL
cdkactions-0.2.3.dist-info/top_level.txt
cdkactions-0.2.3.dist-info/RECORD
